{
  "exercise": "push_up",
  "type": "standard",
  "description": "Chuẩn mực bài chống đẩy - tư thế đúng, biên độ đầy đủ",
  "source": "HLV chuyên nghiệp",
  "frames": [
    {
      "frame": 0,
      "phase": "top",
      "landmarks": [
        { "x": 0.501, "y": 0.153, "z": -0.021, "visibility": 0.998 },
        { "x": 0.498, "y": 0.144, "z": -0.030, "visibility": 0.995 },
        { "x": 0.496, "y": 0.131, "z": -0.038, "visibility": 0.993 },
        { "x": 0.493, "y": 0.122, "z": -0.042, "visibility": 0.991 },
        { "x": 0.508, "y": 0.144, "z": -0.012, "visibility": 0.996 },
        { "x": 0.510, "y": 0.131, "z": -0.005, "visibility": 0.994 },
        { "x": 0.512, "y": 0.122, "z": -0.001, "visibility": 0.992 },
        { "x": 0.442, "y": 0.155, "z": -0.035, "visibility": 0.987 },
        { "x": 0.561, "y": 0.155, "z": -0.006, "visibility": 0.988 },
        { "x": 0.441, "y": 0.146, "z": -0.039, "visibility": 0.983 },
        { "x": 0.562, "y": 0.146, "z": -0.002, "visibility": 0.984 },
        { "x": 0.378, "y": 0.250, "z": -0.052, "visibility": 0.996 },
        { "x": 0.625, "y": 0.250, "z":  0.012, "visibility": 0.997 },
        { "x": 0.350, "y": 0.359, "z": -0.045, "visibility": 0.995 },
        { "x": 0.652, "y": 0.359, "z":  0.005, "visibility": 0.996 },
        { "x": 0.308, "y": 0.448, "z": -0.048, "visibility": 0.986 },
        { "x": 0.694, "y": 0.448, "z":  0.008, "visibility": 0.987 },
        { "x": 0.233, "y": 0.427, "z": -0.051, "visibility": 0.952 },
        { "x": 0.770, "y": 0.427, "z":  0.011, "visibility": 0.953 },
        { "x": 0.218, "y": 0.422, "z": -0.050, "visibility": 0.948 },
        { "x": 0.785, "y": 0.422, "z":  0.010, "visibility": 0.949 },
        { "x": 0.291, "y": 0.388, "z": -0.049, "visibility": 0.975 },
        { "x": 0.711, "y": 0.388, "z":  0.009, "visibility": 0.976 },
        { "x": 0.492, "y": 0.452, "z": -0.035, "visibility": 0.994 },
        { "x": 0.510, "y": 0.452, "z": -0.008, "visibility": 0.995 },
        { "x": 0.640, "y": 0.551, "z": -0.028, "visibility": 0.993 },
        { "x": 0.362, "y": 0.551, "z": -0.015, "visibility": 0.994 },
        { "x": 0.781, "y": 0.649, "z": -0.022, "visibility": 0.990 },
        { "x": 0.221, "y": 0.649, "z": -0.018, "visibility": 0.991 },
        { "x": 0.793, "y": 0.648, "z": -0.024, "visibility": 0.987 },
        { "x": 0.209, "y": 0.648, "z": -0.016, "visibility": 0.988 },
        { "x": 0.802, "y": 0.650, "z": -0.025, "visibility": 0.985 },
        { "x": 0.200, "y": 0.650, "z": -0.015, "visibility": 0.986 }
      ]
    },
    {
      "frame": 1,
      "phase": "bottom",
      "landmarks": [
        { "x": 0.510, "y": 0.168, "z": -0.019, "visibility": 0.997 },
        { "x": 0.506, "y": 0.158, "z": -0.028, "visibility": 0.994 },
        { "x": 0.503, "y": 0.145, "z": -0.035, "visibility": 0.992 },
        { "x": 0.501, "y": 0.137, "z": -0.040, "visibility": 0.990 },
        { "x": 0.517, "y": 0.158, "z": -0.010, "visibility": 0.995 },
        { "x": 0.519, "y": 0.145, "z": -0.003, "visibility": 0.993 },
        { "x": 0.521, "y": 0.137, "z":  0.001, "visibility": 0.991 },
        { "x": 0.450, "y": 0.170, "z": -0.033, "visibility": 0.986 },
        { "x": 0.573, "y": 0.170, "z": -0.004, "visibility": 0.987 },
        { "x": 0.448, "y": 0.161, "z": -0.036, "visibility": 0.982 },
        { "x": 0.575, "y": 0.161, "z":  0.001, "visibility": 0.983 },
        { "x": 0.378, "y": 0.265, "z": -0.055, "visibility": 0.995 },
        { "x": 0.625, "y": 0.265, "z":  0.015, "visibility": 0.996 },
        { "x": 0.355, "y": 0.375, "z": -0.050, "visibility": 0.994 },
        { "x": 0.647, "y": 0.375, "z":  0.010, "visibility": 0.995 },
        { "x": 0.308, "y": 0.465, "z": -0.052, "visibility": 0.985 },
        { "x": 0.694, "y": 0.465, "z":  0.012, "visibility": 0.986 },
        { "x": 0.233, "y": 0.444, "z": -0.055, "visibility": 0.950 },
        { "x": 0.770, "y": 0.444, "z":  0.015, "visibility": 0.951 },
        { "x": 0.218, "y": 0.439, "z": -0.054, "visibility": 0.946 },
        { "x": 0.785, "y": 0.439, "z":  0.014, "visibility": 0.947 },
        { "x": 0.291, "y": 0.405, "z": -0.053, "visibility": 0.974 },
        { "x": 0.711, "y": 0.405, "z":  0.013, "visibility": 0.975 },
        { "x": 0.492, "y": 0.466, "z": -0.033, "visibility": 0.993 },
        { "x": 0.510, "y": 0.466, "z": -0.006, "visibility": 0.994 },
        { "x": 0.640, "y": 0.555, "z": -0.026, "visibility": 0.992 },
        { "x": 0.362, "y": 0.555, "z": -0.013, "visibility": 0.993 },
        { "x": 0.781, "y": 0.652, "z": -0.020, "visibility": 0.989 },
        { "x": 0.221, "y": 0.652, "z": -0.016, "visibility": 0.990 },
        { "x": 0.793, "y": 0.651, "z": -0.022, "visibility": 0.986 },
        { "x": 0.209, "y": 0.651, "z": -0.014, "visibility": 0.987 },
        { "x": 0.802, "y": 0.653, "z": -0.023, "visibility": 0.984 },
        { "x": 0.200, "y": 0.653, "z": -0.013, "visibility": 0.985 }
      ]
    }
  ],
  "angles": {
    "left_elbow": { "top": 178, "bottom": 92 },
    "right_elbow": { "top": 178, "bottom": 92 },
    "left_shoulder": { "top": 90, "bottom": 42 },
    "right_shoulder": { "top": 90, "bottom": 42 },
    "hip_angle": { "top": 178, "bottom": 176 },
    "knee_angle": { "top": 177, "bottom": 176 }
  }
}
